rat/__init__.py
rat/server.py
rat_django_runner-0.1.0.dist-info/LICENSE
rat_django_runner-0.1.0.dist-info/METADATA
rat_django_runner-0.1.0.dist-info/WHEEL
rat_django_runner-0.1.0.dist-info/top_level.txt
rat_django_runner-0.1.0.dist-info/RECORD
