Metadata-Version: 2.1
Name: rat-django-runner
Version: 0.1.0
Summary: Django runserver uchun IP va portni oson boshqarish kutubxonasi
Home-page: https://github.com/sharifjon/rat
Author: Sharifjom Mo'minov
Author-email: mominovsharif@gmail.com
Classifier: Programming Language :: Python :: 3
Classifier: Framework :: Django
Classifier: License :: OSI Approved :: MIT License
Requires-Python: >=3.6
License-File: LICENSE
